OASYS1_shadow4-0.0.88-py3.8-nspkg.pth
orangecontrib/shadow4/menu/__init__.py
orangecontrib/shadow4/menu/ow_shadow4_menu.py
orangecontrib/shadow4/util/__init__.py
orangecontrib/shadow4/util/python_script.py
orangecontrib/shadow4/util/shadow4_objects.py
orangecontrib/shadow4/util/shadow4_util.py
orangecontrib/shadow4/widgets/compatibility/__init__.py
orangecontrib/shadow4/widgets/compatibility/ow_shadow3_beam_to_shadow4_beam.py
orangecontrib/shadow4/widgets/compatibility/ow_shadow4_beam_to_shadow3_beam.py
orangecontrib/shadow4/widgets/compatibility/ow_shadow_compare_beam3_beam4.py
orangecontrib/shadow4/widgets/compatibility/icons/beam3to4.png
orangecontrib/shadow4/widgets/compatibility/icons/beam4to3.png
orangecontrib/shadow4/widgets/compatibility/icons/compare3to4.png
orangecontrib/shadow4/widgets/compatibility/icons/compatibility.png
orangecontrib/shadow4/widgets/gui/__init__.py
orangecontrib/shadow4/widgets/gui/ow_abstract_lens.py
orangecontrib/shadow4/widgets/gui/ow_automatic_element.py
orangecontrib/shadow4/widgets/gui/ow_electron_beam.py
orangecontrib/shadow4/widgets/gui/ow_generic_element.py
orangecontrib/shadow4/widgets/gui/ow_optical_element.py
orangecontrib/shadow4/widgets/gui/ow_optical_element_with_surface_shape.py
orangecontrib/shadow4/widgets/gui/ow_optical_element_with_surface_shape_render.py
orangecontrib/shadow4/widgets/gui/plots.py
orangecontrib/shadow4/widgets/gui/misc/bragg_usage.png
orangecontrib/shadow4/widgets/gui/misc/crl_help.png
orangecontrib/shadow4/widgets/gui/misc/lens_help.png
orangecontrib/shadow4/widgets/gui/misc/premlayer_usage.png
orangecontrib/shadow4/widgets/gui/misc/prerefl_usage.png
orangecontrib/shadow4/widgets/gui/misc/vls_pgm_layout.png
orangecontrib/shadow4/widgets/gui/misc/vls_pgm_usage.png
orangecontrib/shadow4/widgets/optics/__init__.py
orangecontrib/shadow4/widgets/optics/ow_beam_movements.py
orangecontrib/shadow4/widgets/optics/ow_crl.py
orangecontrib/shadow4/widgets/optics/ow_crystal.py
oasys1_shadow4-0.0.88.dist-info/LICENSE
oasys1_shadow4-0.0.88.dist-info/METADATA
oasys1_shadow4-0.0.88.dist-info/WHEEL
oasys1_shadow4-0.0.88.dist-info/entry_points.txt
oasys1_shadow4-0.0.88.dist-info/namespace_packages.txt
oasys1_shadow4-0.0.88.dist-info/top_level.txt
oasys1_shadow4-0.0.88.dist-info/RECORD
